montage/__init__.py
montage/montager.py
montage/utilities.py
quick_montage-0.0.3.dist-info/LICENSE
quick_montage-0.0.3.dist-info/METADATA
quick_montage-0.0.3.dist-info/WHEEL
quick_montage-0.0.3.dist-info/top_level.txt
quick_montage-0.0.3.dist-info/RECORD
