Metadata-Version: 2.1
Name: quick-montage
Version: 0.0.3
Summary: Quick montage creator for photos in a given directory
Home-page: https://github.com/mateczentye/montage
Author: Máté I. Czentye
Author-email: czentyemate@gmail.com
License: MIT
License-File: LICENSE
